tpds_extension/asym_auth/extension.yaml
tpds_extension/asym_auth/setup.py
tpds_extension/asym_auth/version.py
tpds_extension/asym_auth/TrustFlex/Asymmetric Authentication.ipynb
tpds_extension/asym_auth/TrustFlex/cust_def_device.c
tpds_extension/asym_auth/TrustFlex/cust_def_device.h
tpds_extension/asym_auth/TrustFlex/cust_def_signer.c
tpds_extension/asym_auth/TrustFlex/cust_def_signer.h
tpds_extension/asym_auth/TrustFlex/firmware.zip
tpds_extension/asym_auth/TrustFlex/assets/Asymmetric Authentication.md
tpds_extension/asym_auth/TrustFlex/assets/images/asymmetric auth.png
tpds_extension/asym_auth/TrustFlex/assets/images/c-snippet.PNG
tpds_extension/asym_auth/TrustFlex/assets/images/crypto-assets.png
tpds_extension/asym_auth/TrustFlex/assets/images/td-Accessory-Asymmetric-Auth.png
tpds_extension/asym_auth/TrustFlex/assets/images/usecase_steps.png
tpds_extension/asym_auth/TrustFlex/assets/python/asymmetric_authentication.py
tpds_extension_spg_asym_auth-2.0.5.dist-info/METADATA
tpds_extension_spg_asym_auth-2.0.5.dist-info/WHEEL
tpds_extension_spg_asym_auth-2.0.5.dist-info/top_level.txt
tpds_extension_spg_asym_auth-2.0.5.dist-info/RECORD
